TCore/__init__.py
TProject/__init__.py
TCore_Thijs_GH-0.0.1.dist-info/LICENSE
TCore_Thijs_GH-0.0.1.dist-info/METADATA
TCore_Thijs_GH-0.0.1.dist-info/WHEEL
TCore_Thijs_GH-0.0.1.dist-info/top_level.txt
TCore_Thijs_GH-0.0.1.dist-info/RECORD
