Metadata-Version: 2.1
Name: TCore-Thijs-GH
Version: 0.0.1
Summary: TCore
Home-page: https://github.com/ThijsieJWW/TCore
Author: Thijs van Straaten
Author-email: thijs.gh.contact@gmail.com
License: UNKNOWN
Project-URL: Bug Tracker, https://github.com/ThijsieJWW/TCore/issues
Platform: UNKNOWN
Classifier: Programming Language :: Python :: 3
Requires-Python: ==3.9
License-File: LICENSE
